fim/__init__.py
fim/_fim.pyi
fim/_fim.so
fimage_python-0.1.0.dist-info/WHEEL
fimage_python-0.1.0.dist-info/METADATA
fimage_python-0.1.0.dist-info/RECORD
