Metadata-Version: 2.1
Name: fimage-python
Author: AI for Oncology Research Group
Home-page: https://github.com/NKI-AI/aifo-openmidnight
License: Apache-2.0
Summary: Fast Image processing library with lazy evaluation
Requires-Python: >=3.10
Requires-Dist: numpy
Version: 0.1.0
